libmi/__init__.py
libmi-0.2.0.dist-info/METADATA
libmi-0.2.0.dist-info/WHEEL
libmi-0.2.0.dist-info/top_level.txt
libmi-0.2.0.dist-info/RECORD
